{
  "type": "FeatureCollection",
  "features": [
    {
      "type": "Feature",
      "properties": {
        "name": "Château de Murviel-lès-Béziers",
        "description": "Château situé à Murviel-lès-Béziers."
      },
      "geometry": {
        "type": "Point",
        "coordinates": [3.14354, 43.43992]
      }
    }
  ]
}
